Metadata-Version: 2.1
Name: ms2query
Version: 1.5.4
Summary: Tool to query MS/MS spectra against mass spectral library
Home-page: https://github.com/iomega/ms2query
Author: Netherlands eScience Center
Author-email: 
License: Apache Software License 2.0
Platform: UNKNOWN
Requires-Python: >=3.9
License-File: LICENSE
Requires-Dist: matchms<=0.26.4,>=0.24.0
Requires-Dist: numpy
Requires-Dist: torch<2.6
Requires-Dist: spec2vec>=0.6.0
Requires-Dist: h5py
Requires-Dist: pyarrow
Requires-Dist: scikit-learn
Requires-Dist: ms2deepscore==2.0.0
Requires-Dist: gensim>=4.0.0
Requires-Dist: pandas
Requires-Dist: tqdm
Requires-Dist: matplotlib
Requires-Dist: skl2onnx
Requires-Dist: onnx<1.16.2
Requires-Dist: onnxruntime<1.16
Provides-Extra: dev
Requires-Dist: bump2version; extra == "dev"
Requires-Dist: isort>=5.1.0; extra == "dev"
Requires-Dist: prospector; extra == "dev"
Requires-Dist: pytest; extra == "dev"
Requires-Dist: pytest-cov; extra == "dev"
Requires-Dist: sphinx!=3.2.0,<4.0.0,>=3.0.0; extra == "dev"
Requires-Dist: sphinx-rtd-theme; extra == "dev"
Requires-Dist: sphinxcontrib-apidoc; extra == "dev"
Requires-Dist: yapf; extra == "dev"
Requires-Dist: rdkit; extra == "dev"
